Metadata-Version: 2.4
Name: fastapi_kick
Version: 0.1.1
Summary: FastAPI app scaffolder with health, modules, and Postgres
Home-page: https://example.com/fastapi_kick
Author: Your Name
Author-email: you@example.com
Requires-Dist: fastapi
Requires-Dist: uvicorn
Requires-Dist: sqlalchemy
Requires-Dist: python-dotenv
Requires-Dist: asyncpg
Requires-Dist: psycopg2-binary
Dynamic: author
Dynamic: author-email
Dynamic: description
Dynamic: description-content-type
Dynamic: home-page
Dynamic: requires-dist
Dynamic: summary
